litestar_mqtt/__init__.py
litestar_mqtt/config.py
litestar_mqtt/handlers.py
litestar_mqtt/litemqtt.py
litestar_mqtt-1.0.0.dist-info/LICENSE
litestar_mqtt-1.0.0.dist-info/METADATA
litestar_mqtt-1.0.0.dist-info/WHEEL
litestar_mqtt-1.0.0.dist-info/RECORD
