Metadata-Version: 2.1
Name: litestar-mqtt
Version: 1.0.0
Summary: 
Author: Alessandro Ferrini
Author-email: im@alessandroferrini.com
Requires-Python: >=3.8,<4.0
Classifier: Programming Language :: Python :: 3
Classifier: Programming Language :: Python :: 3.8
Classifier: Programming Language :: Python :: 3.9
Classifier: Programming Language :: Python :: 3.10
Classifier: Programming Language :: Python :: 3.11
Requires-Dist: gmqtt (>=0.6.12,<0.7.0)
Requires-Dist: litestar (>=2.0.0,<3.0.0)
Requires-Dist: pydantic (>=2.0.0,<3.0.0)
Requires-Dist: pydantic-settings (>=2.0.0,<3.0.0)
